<?xml version="1.0" encoding="utf-8" standalone="yes" ?>
<T3locallang>
	<meta type="array">
		<type>module</type>
		<description>Language labels for the YAG - Yet Another Gallery extension</description>
	</meta>
	<data type="array">
		<languageKey index="default" type="array">
		
		
		    <!-- GENERAL labels -->
            <label index="general.edit">Edit</label>
            <label index="general.delete">Delete</label>
            <label index="general.required">Required</label>
            <label index="general.submit">Submit</label>
            <label index="general.save">Save</label>
            
            
            <!-- GALLERY labels -->
            <label index="gallery.title">Title</label>
            <label index="gallery.description">Description</label>
            <label index="gallery.albums">Contained albums</label>
            <lable index="gallery.date">Date</lable>
            
            
            <!-- GALLERY links -->
            <label index="gallery.links.backToGalleryOverview">Back to gallery overview</label>
            <label index="gallery.links.backToGallery">Back to gallery</label>
            
            
            <!-- GALLERY index labels -->
		    <label index="gallery.index.header">Gallery overview</label>
			<label index="gallery.index.infotext">List of galleries currently available:</label>
			<label index="gallery.index.createOther">Create another gallery</label>
			<label index="gallery.index.createFirst">Create your first gallery</label>
			
			
			<!-- GALLERY delete labels -->
			<label index="gallery.delete.header">Delete gallery: </label>
			<label index="gallery.delete.defaultHeader">Delete gallery</label>
			<label index="gallery.delete.galleryHasBeenDeleted">Gallery has been deleted</label>
			<label index="gallery.delete.reallyDelete">Delete Gallery!</label>
			<label index="gallery.delete.infotext">Do you really want to delete this gallery: </label>
			<label index="gallery.delete.allsubswillbedeleted">(all contained albums will be deleted!)</label>
			
			
			<!-- GALLERY edit labels -->
			<label index="gallery.edit.header">Edit gallery</label>
			<label index="gallery.edit.propertiesheader">Edit gallery properties</label>
			<label index="gallery.edit.infotext">Update information about your new gallery below:</label>
			<label index="gallery.edit.removealbumheader">Remove albums from gallery</label>
			<label index="gallery.edit.removealbumlink">Remove album from gallery</label>
			<label index="gallery.edit.removeaddalbumheader">Remove / Add album from or to gallery</label>
			<label index="gallery.edit.removeaddalbumsinfotext">Select the albums that should be attached to your gallery</label>
			
			
		</languageKey>
		
		
		<languageKey index="de" type="array">
		
		
		    <!-- GENERAL labels -->
            <label index="general.delete">Löschen</label>
            <label index="general.edit">Bearbeiten</label>
            <label index="general.required">Pflichtfeld</label>
            <label index="general.submit">Abschicken</label>
            <label index="general.save">Speichern</label>
            
            
            <!-- GALLERY labels -->
            <label index="gallery.title">Titel</label>
            <label index="gallery.description">Beschreibung</label>
            <label index="gallery.albums">Beinhaltete Alben</label>
            <lable index="gallery.date">Datum</lable>
            
            
            <!-- GALLERY links -->
            <label index="gallery.links.backToGalleryOverview">Zurück zur Gallery Übersicht</label>
            <label index="gallery.links.backToGallery">Zurück zur Gallery</label>
            
            
            <!-- GALLERY index labels -->
		    <label index="gallery.index.header">Galerie-Übersicht</label>
		    <label index="gallery.index.infotext">Übersicht derzeit verfügbarer Galerien:</label>
		    <label index="gallery.index.createOther">Eine weitere Galerie anlegen</label>
		    <label index="gallery.index.createFirst">Erste Galerie anlegen</label>
		    
		    
		    <!-- GALLERY delete labels -->
            <label index="gallery.delete.header">Galerie löschen: </label>
            <label index="gallery.delete.defaultHeader">Galerie löschen</label>
            <label index="gallery.delete.galleryHasBeenDeleted">Galerie wurde gelöscht</label>
            <label index="gallery.delete.reallyDelete">Galerie löschen!</label>
            <label index="gallery.delete.infotext">Wollen Sie diese Galerie wirklich löschen: </label>
            <label index="gallery.delete.allsubswillbedeleted">(alle Alben in dieser Galerie werden gelöscht!)</label>
            
            
            <!-- GALLERY edit labels -->
            <label index="gallery.edit.header">Galerie bearbeiten</label>
            <label index="gallery.edit.propertiesheader">Galerieeigenschaften bearbeiten</label>
            <label index="gallery.edit.infotext">Hier können Sie die Eigenschaften der Galerie bearbeiten:</label>
            <label index="gallery.edit.removealbumheader">Alben aus Galerie löschen</label>
            <label index="gallery.edit.removealbumlink">Album aus Galerie entfernen</label>
            <label index="gallery.edit.removeaddalbumheader">Alben zur Galerie hinzufügen oder entfernen</label>
            <label index="gallery.edit.removeaddalbumsinfotext">Hier können Sie Alben zur Galerie hinzufügen oder entfernen</label>
		    
		    
		</languageKey>
	</data>
</T3locallang>